mopidy_notify/__init__.py
mopidy_notify/ext.conf
mopidy_notify/frontend.py
mopidy_notify/icon.py
mopidy_notify/notifications.py
mopidy_notify-0.2.2.dist-info/licenses/LICENSE
mopidy_notify-0.2.2.dist-info/METADATA
mopidy_notify-0.2.2.dist-info/WHEEL
mopidy_notify-0.2.2.dist-info/entry_points.txt
mopidy_notify-0.2.2.dist-info/top_level.txt
mopidy_notify-0.2.2.dist-info/RECORD
